borealis/__init__.py
borealis/docker_task.py
borealis/fireworker.py
borealis/gce.py
borealis/setup/borealis-fireworker.service
borealis/setup/example_mongo_ssh.sh
borealis/setup/example_my_launchpad.yaml
borealis/setup/how-to-install-gce-server.txt
borealis/setup/requirements.txt
borealis/setup/startup.sh
borealis/util/__init__.py
borealis/util/data.py
borealis/util/filepath.py
borealis/util/gcp.py
borealis/util/log_filter.py
borealis/util/storage.py
borealis_fireworks-0.12.0.dist-info/LICENSE
borealis_fireworks-0.12.0.dist-info/METADATA
borealis_fireworks-0.12.0.dist-info/WHEEL
borealis_fireworks-0.12.0.dist-info/entry_points.txt
borealis_fireworks-0.12.0.dist-info/top_level.txt
borealis_fireworks-0.12.0.dist-info/RECORD
