Metadata-Version: 2.1
Name: borealis-fireworks
Version: 0.12.0
Summary: Run FireWorks workflows in Google Cloud
Home-page: https://github.com/CovertLab/borealis
Author: Jerry Morrison
Author-email: j.erry.morrison@gmail.com
License: MIT
Project-URL: Source, https://github.com/CovertLab/borealis
Project-URL: Documentation, https://github.com/CovertLab/borealis#borealis
Project-URL: Changelog, https://github.com/CovertLab/borealis/blob/master/docs/changes.md
Keywords: fireworks workflow
Classifier: Development Status :: 3 - Alpha
Classifier: Intended Audience :: Developers
Classifier: Intended Audience :: Information Technology
Classifier: Intended Audience :: Science/Research
Classifier: Intended Audience :: System Administrators
Classifier: License :: OSI Approved :: MIT License
Classifier: Operating System :: OS Independent
Classifier: Programming Language :: Python
Classifier: Programming Language :: Python :: 3 :: Only
Classifier: Programming Language :: Python :: 3.8
Classifier: Programming Language :: Python :: 3.9
Classifier: Programming Language :: Python :: 3.10
Classifier: Programming Language :: Python :: 3.11
Requires-Python: >=3.8, <4
License-File: LICENSE
Requires-Dist: google-cloud-logging (>=2.0.0)
Requires-Dist: google-cloud-storage (>=1.28.0)
Requires-Dist: docker (>=4.1.0)
Requires-Dist: FireWorks (>=1.9.7)
Requires-Dist: requests (>=2.22.0)
Requires-Dist: ruamel.yaml (>=0.16.9)
